pubgReports/DISCORDCONFIG.csv
pubgReports/PLAYERS.csv
pubgReports/PUBGstats.py
pubgReports/README.md
pubgReports/TOKENS.csv
pubgReports/bot.py
pubgReports/config.py
pubgReports/registration.py
pubgReports/run
pubgReports/scriptpubg
pubgReports/__pycache__/PUBGstats.cpython-36.pyc
pubgReports/__pycache__/registration.cpython-36.pyc
pubgReports/matchdata/.gitkeep
pubgReports/playerdata/.gitkeep
pubg_reports-0.0.0.1.4.1.data/data/DISCORDCONFIG.csv
pubg_reports-0.0.0.1.4.1.data/data/PLAYERS.csv
pubg_reports-0.0.0.1.4.1.data/data/TOKENS.csv
pubg_reports-0.0.0.1.4.1.dist-info/METADATA
pubg_reports-0.0.0.1.4.1.dist-info/WHEEL
pubg_reports-0.0.0.1.4.1.dist-info/entry_points.txt
pubg_reports-0.0.0.1.4.1.dist-info/top_level.txt
pubg_reports-0.0.0.1.4.1.dist-info/RECORD
