Metadata-Version: 2.1
Name: pubg-reports
Version: 0.0.0.1.4.1
Summary: A discord bot that reports PUBG match stats to a discord server
Home-page: https://github.com/SulimanCS/pubg-discord-stats-integration-bot
Author: Suliman Alsarraf
Author-email: sulimanAlsarraf@gmail.com
License: MIT
Platform: UNKNOWN
Classifier: License :: OSI Approved :: MIT License
Classifier: Programming Language :: Python :: 3.6
Classifier: Programming Language :: Python :: 3.7
Requires-Dist: requests
Requires-Dist: discord.py
